Metadata-Version: 2.1
Name: odoo8-addon-purchase-discount
Version: 8.0.1.1.0.99.dev31
Summary: Purchase order lines with discounts
Home-page: UNKNOWN
Author: Tiny, Acysos S.L., Serv. Tecnol. Avanzados - Pedro M. Baeza, AvanzOSC, S.L., Odoo Community Association (OCA)
Author-email: support@odoo-community.org
License: AGPL-3
Platform: UNKNOWN
Classifier: Programming Language :: Python
Classifier: Framework :: Odoo
Classifier: Framework :: Odoo :: 8.0
Classifier: License :: OSI Approved :: GNU Affero General Public License v3
Requires-Python: ~=2.7
Requires-Dist: odoo (<9.0a,>=8.0a)
